.env
.flake8
.gitignore
.gitlab-ci.yml
.isort.cfg
.pydocstyle
.readthedocs.yml
CHANGELOG.rst
LICENSE
README.md
build-dep.sh
doc8.ini
install_requirements.sh
pkglist
plot_benchmark.py
plot_benchmark_fir.py
pytest.ini
setup.cfg
setup.py
tox.ini
docs/Makefile
docs/make.bat
docs/requirements.txt
docs/source/api.rst
docs/source/changelog.rst
docs/source/conf.py
docs/source/index.rst
docs/source/license.rst
numpy_ipps/__init__.py
numpy_ipps/broadcast.py
numpy_ipps/complex.py
numpy_ipps/conversion.py
numpy_ipps/exponential.py
numpy_ipps/floating.py
numpy_ipps/initialization.py
numpy_ipps/integer.py
numpy_ipps/logical.py
numpy_ipps/policies.py
numpy_ipps/rational.py
numpy_ipps/rounding.py
numpy_ipps/signal.py
numpy_ipps/special.py
numpy_ipps/statistical.py
numpy_ipps/support.py
numpy_ipps/tools.py
numpy_ipps/trigonometric.py
numpy_ipps/utils.py
numpy_ipps.egg-info/PKG-INFO
numpy_ipps.egg-info/SOURCES.txt
numpy_ipps.egg-info/dependency_links.txt
numpy_ipps.egg-info/not-zip-safe
numpy_ipps.egg-info/requires.txt
numpy_ipps.egg-info/top_level.txt
numpy_ipps/_detail/__init__.py
numpy_ipps/_detail/debug.py
numpy_ipps/_detail/dispatch.py
numpy_ipps/_detail/dtype.py
numpy_ipps/_detail/libipp.py
numpy_ipps/_detail/metaclass/__init__.py
numpy_ipps/_detail/metaclass/binaries.py
numpy_ipps/_detail/metaclass/selector.py
numpy_ipps/_detail/metaclass/unaries.py
numpy_ipps/constants/__init__.py
numpy_ipps/constants/maths/__init__.py
numpy_ipps/constants/maths/float32.py
numpy_ipps/constants/maths/float64.py
numpy_ipps/constants/maths/_detail/__init__.py
numpy_ipps/constants/maths/_detail/generators.py
numpy_ipps/constants/physics/__init__.py
numpy_ipps/constants/physics/float32.py
numpy_ipps/constants/physics/float64.py
numpy_ipps/filtering/__init__.py
numpy_ipps/filtering/fir.py
numpy_ipps/filtering/iir.py
numpy_ipps/filtering/median.py
numpy_ipps/lib/linux/libippcore.so
numpy_ipps/lib/linux/libipps.so
numpy_ipps/lib/linux/libippse9.so
numpy_ipps/lib/linux/libippsk0.so
numpy_ipps/lib/linux/libippsl9.so
numpy_ipps/lib/linux/libippsm7.so
numpy_ipps/lib/linux/libippsn0.so
numpy_ipps/lib/linux/libippsn8.so
numpy_ipps/lib/linux/libippsy8.so
numpy_ipps/lib/linux/libippvm.so
