Metadata-Version: 2.1
Name: numpy-ipps
Version: 2.2.1.dev0
Summary: Numpy Intel IPP signal.
Home-page: https://gitlab.com/fblanchet/numpy_ipps
Author: Florian Blanchet
Author-email: florian.blanchet.supop@gmail.com
License: Apache Software License
Project-URL: Documentation, https://numpy-intel-ipp-signal.readthedocs.io
Project-URL: Bug Tracker, https://gitlab.com/fblanchet/numpy_ipps/issues
Platform: UNKNOWN
Classifier: Intended Audience :: Science/Research
Classifier: License :: OSI Approved :: Apache Software License
Classifier: Programming Language :: Python :: 3
Classifier: Programming Language :: Python :: 3.5
Classifier: Programming Language :: Python :: 3.6
Classifier: Programming Language :: Python :: 3.7
Classifier: Programming Language :: Python :: 3.8
Classifier: Programming Language :: Python :: 3.9
Classifier: Programming Language :: Python
Classifier: Topic :: Scientific/Engineering :: Physics
Requires-Python: <4,>=3.5
Provides-Extra: dev
